selenium_make/__init__.py
selenium_make/auto_setup.py
selenium_make-0.0.3.dist-info/METADATA
selenium_make-0.0.3.dist-info/WHEEL
selenium_make-0.0.3.dist-info/entry_points.txt
selenium_make-0.0.3.dist-info/licenses/LICENSE
selenium_make-0.0.3.dist-info/RECORD
