Metadata-Version: 2.4
Name: selenium-make
Version: 0.0.3
Summary: A simple CLI tool to set up Selenium scripts and install browser drivers for automation.
Project-URL: Homepage, https://github.com/dilrajs616/selenium-make
Project-URL: Issues, https://github.com/dilrajs616/selenium-make/discussions
Author-email: Dilraj Singh <dilraj082@gmail.com>
License: MIT
License-File: LICENSE
Keywords: automation,chrome,cli,firefox,selenium
Classifier: Intended Audience :: Developers
Classifier: License :: OSI Approved :: MIT License
Classifier: Programming Language :: Python :: 3
Classifier: Topic :: Software Development :: Libraries :: Python Modules
Requires-Python: >=3.8
